currency/__init__.py
currencycomma2/__init__.py
currencycomma2-0.1.dist-info/METADATA
currencycomma2-0.1.dist-info/WHEEL
currencycomma2-0.1.dist-info/top_level.txt
currencycomma2-0.1.dist-info/RECORD
