Metadata-Version: 2.1
Name: currencycomma2
Version: 0.1
Summary: A package for formatting currency values
Home-page: https://github.com/miladmirza75/currency
Author: Milad Mirza
Author-email: Miladmirza75@gmail.com
License: UNKNOWN
Platform: UNKNOWN
